data_transformation_library_paula/__init__.py
data_transformation_library_paula/transformation_functions.py
data_transformation_library_paula/validators.py
data_transformation_library_paula-0.1.4.dist-info/METADATA
data_transformation_library_paula-0.1.4.dist-info/WHEEL
data_transformation_library_paula-0.1.4.dist-info/RECORD
