Metadata-Version: 2.1
Name: data-transformation-library-paula
Version: 0.1.4
Summary: The `data-transformation-library-paula` is a Python package focused on providing essential tools for matrix operations and data transformations. These functions are fundamental for handling and processing data in areas like machine learning, signal processing, and image processing.
Author: Paula
Author-email: paula.valaityte@gmail.com
Requires-Python: >=3.12,<4.0
Classifier: Programming Language :: Python :: 3
Classifier: Programming Language :: Python :: 3.12
Requires-Dist: numpy (>=1.26.4,<2.0.0)
